ews_nox/__init__.py
ews_nox/helpers.py
ews_nox/version.py
ews_nox/tests/__init__.py
ews_nox/tests/test.py
ews_nox/tests/test_version.py
ews_nox/utilities/__init__.py
ews_nox/utilities/git.py
ews_nox/utilities/hosts.py
ews_nox/utilities/installation.py
ews_nox/utilities/misc.py
ews_nox/utilities/package.py
ews_nox-20240301.dist-info/LICENSE
ews_nox-20240301.dist-info/METADATA
ews_nox-20240301.dist-info/WHEEL
ews_nox-20240301.dist-info/top_level.txt
ews_nox-20240301.dist-info/RECORD
