Metadata-Version: 2.1
Name: ews-nox
Version: 20240301
Summary: A simple TOML configuration for EWS settings
Author-email: EWS Consulting - Testing Center <github@ews-consulting.com>
License: MIT License
Project-URL: Homepage, https://github.com/EWS-Consulting-Public/ews-nox
Project-URL: Source, https://github.com/EWS-Consulting-Public/ews-nox
Project-URL: Documentation, https://mb.ews.tools/ews-nox
Keywords: helpers,nox,EWS
Classifier: License :: OSI Approved :: MIT License
Classifier: Operating System :: Unix
Classifier: Programming Language :: Python
Classifier: Programming Language :: Python :: 3.10
Classifier: Programming Language :: Python :: 3.11
Classifier: Programming Language :: Python :: 3.12
Requires-Python: >=3.10
License-File: LICENSE
Requires-Dist: nox
Requires-Dist: python-dotenv
Requires-Dist: tomlkit
Provides-Extra: dev
Provides-Extra: ews
Requires-Dist: ews-core-config >=20230301 ; extra == 'ews'
